{
  "product": "Aurora Galactica",
  "version": "1.4.1-beta.1",
  "versionLine": "1.4.1-beta.1",
  "versionScheme": "semver-prerelease",
  "label": "1.4.1-beta.1+build.1168.sha.edd6a736.beta",
  "buildNumber": "1168",
  "commit": "edd6a73600a9b035b80d023475b9d976039b132b",
  "shortCommit": "edd6a736",
  "branch": "beta",
  "state": "beta@edd6a736 clean",
  "releaseChannel": "production beta",
  "publicArtifactBoundaryEnabled": true,
  "dirty": false,
  "dirtyFiles": [],
  "builtAtUtc": "2026-06-11T17:22:32.022Z",
  "builtAtEt": "Jun 11 2026, 1:22 PM EDT",
  "platform": {
    "key": "platinum",
    "name": "Platinum",
    "version": "1.4.1",
    "releaseTrack": "production-family",
    "compatibility": "platinum-1.4",
    "notes": "Platform-owned shell, release lanes, docs, replay, services, and host contract.",
    "media": {
      "arcadeMusicPlaylistId": "PLWDxjyS0X-zlKJsel_7Kg3ALGlSD89zSH"
    },
    "auth": {
      "nonProductionTestPilotEmails": [],
      "nonProductionTestPilotUserIds": []
    }
  },
  "applications": [
    {
      "gameKey": "aurora-galactica",
      "title": "Aurora Galactica",
      "version": "1.4.1",
      "versionLine": "1.4.1",
      "releaseTrack": "production-family",
      "runtimeStatus": "playable",
      "platformCompatibility": "platinum-1.4",
      "launchPolicy": "production-capable"
    },
    {
      "gameKey": "galaxy-guardians-preview",
      "title": "Galaxy Guardians",
      "version": "0.1.0-preview",
      "versionLine": "0.1.0 preview",
      "releaseTrack": "playable-preview",
      "runtimeStatus": "production-playable-preview",
      "platformCompatibility": "platinum-1.4",
      "launchPolicy": "production-preview-playable"
    }
  ],
  "development": {
    "baseVersion": "1.4.1",
    "iteration": 1,
    "versionLine": "1.4.1.1",
    "releaseTrack": "hosted-dev-increment",
    "notes": "Hosted /dev uses a fourth visible segment to count accumulated production-quality follow-through increments while package.json remains SemVer."
  },
  "supabaseConfigured": true,
  "latestReleaseNote": {
    "version": "1.4.1",
    "date": "2026-06-11",
    "title": "1.4.1 production quality release",
    "summary": "Promotes the accepted 1.4.1 beta review as a production quality release with Stage 3 challenge-stage gameplay keepers, beta sign-in repair, audio/theme lane clarity, public-safe foreground audio balance, refreshed security evidence, and stronger release gates while keeping score submission guarded pending server-side validation.",
    "sourceDoc": "RELEASE_NOTE_1.4.1_PRODUCTION.md"
  },
  "promotedFromState": "main@edd6a736 clean"
}
